<annotation>
	<folder>image</folder>
	<filename>100001488.bmp</filename>
	<path>C:\Users\32085\Desktop\DATA\image\100001488.bmp</path>
	<source>
		<database>Unknown</database>
	</source>
	<size>
		<width>416</width>
		<height>608</height>
		<depth>3</depth>
	</size>
	<segmented>0</segmented>
	<object>
		<name>warcraft</name>
		<pose>Unspecified</pose>
		<truncated>0</truncated>
		<difficult>0</difficult>
		<bndbox>
			<xmin>63</xmin>
			<ymin>104</ymin>
			<xmax>100</xmax>
			<ymax>342</ymax>
		</bndbox>
	</object>
	<object>
		<name>warcraft</name>
		<pose>Unspecified</pose>
		<truncated>1</truncated>
		<difficult>0</difficult>
		<bndbox>
			<xmin>121</xmin>
			<ymin>51</ymin>
			<xmax>416</xmax>
			<ymax>114</ymax>
		</bndbox>
	</object>
	<object>
		<name>warcraft</name>
		<pose>Unspecified</pose>
		<truncated>0</truncated>
		<difficult>0</difficult>
		<bndbox>
			<xmin>56</xmin>
			<ymin>408</ymin>
			<xmax>403</xmax>
			<ymax>471</ymax>
		</bndbox>
	</object>
	<object>
		<name>warcraft</name>
		<pose>Unspecified</pose>
		<truncated>0</truncated>
		<difficult>0</difficult>
		<bndbox>
			<xmin>49</xmin>
			<ymin>507</ymin>
			<xmax>396</xmax>
			<ymax>576</ymax>
		</bndbox>
	</object>
</annotation>
